zabbix_lld/__init__.py
zabbix_lld/utils.py
zabbix_lld/disk.py
zabbix_lld-0.2.dist-info/top_level.txt
zabbix_lld-0.2.dist-info/metadata.json
zabbix_lld-0.2.dist-info/METADATA
zabbix_lld-0.2.dist-info/WHEEL
zabbix_lld-0.2.dist-info/entry_points.txt
zabbix_lld-0.2.dist-info/DESCRIPTION.rst
zabbix_lld-0.2.dist-info/RECORD
