Metadata-Version: 2.0
Name: zabbix-lld
Version: 0.2
Summary: Low level discovery functions for Zabbix
Home-page: https://bitbucket.org/asenci/zabbix_lld
Author: Andre Sencioles
Author-email: asenci@gmail.com
License: ISC License
Platform: UNKNOWN
